{"mActivityList":[{"mActiveTime":3868910,"mActiveTimeType":0,"mCalorie":285.75,"mCategory":204,"mDetailInfoId":"c3bf5536-e953-43ce-b4da-2a96c4ad2062","mDistance":5486.6396,"mDuration":3868000,"mEndTime":30813000,"mStartTime":26945000,"mType":1001},{"mActiveTime":2793568,"mActiveTimeType":0,"mCalorie":197.98999,"mCategory":204,"mDetailInfoId":"ba7a1b1a-8889-4c1f-a7bf-a3e4dea4d448","mDistance":3773.54,"mDuration":2793000,"mEndTime":33790000,"mStartTime":30997000,"mType":1001}],"mAdaptiveGoal":0,"mIsGoalAchieved":true,"mIsMostActiveAchieved":false,"mMostActiveMinutes":360,"mStreakDayCount":0,"mUnitDataList":[{"distance":95.96913,"mCalorie":4.8830237,"mOthersTime":0,"mRunTime":0,"mStartTime":26400000,"mTimeUnit":600000,"mWalkTime":69338,"runStep":0,"walkStep":118},{"distance":850.8814,"mCalorie":44.314804,"mOthersTime":0,"mRunTime":0,"mStartTime":27000000,"mTimeUnit":600000,"mWalkTime":600000,"runStep":0,"walkStep":1110},{"distance":850.8814,"mCalorie":44.314804,"mOthersTime":0,"mRunTime":0,"mStartTime":27600000,"mTimeUnit":600000,"mWalkTime":600000,"runStep":0,"walkStep":1129},{"distance":850.8814,"mCalorie":44.314804,"mOthersTime":0,"mRunTime":0,"mStartTime":28200000,"mTimeUnit":600000,"mWalkTime":600000,"runStep":0,"walkStep":1128},{"distance":850.8814,"mCalorie":44.314804,"mOthersTime":0,"mRunTime":0,"mStartTime":28800000,"mTimeUnit":600000,"mWalkTime":600000,"runStep":0,"walkStep":1107},{"distance":850.8814,"mCalorie":44.314804,"mOthersTime":0,"mRunTime":0,"mStartTime":29400000,"mTimeUnit":600000,"mWalkTime":600000,"runStep":0,"walkStep":1092},{"distance":850.8814,"mCalorie":44.314804,"mOthersTime":0,"mRunTime":0,"mStartTime":30000000,"mTimeUnit":600000,"mWalkTime":600000,"runStep":0,"walkStep":1077},{"distance":623.66016,"mCalorie":32.535625,"mOthersTime":0,"mRunTime":0,"mStartTime":30600000,"mTimeUnit":600000,"mWalkTime":456907,"runStep":0,"walkStep":756},{"distance":810.47754,"mCalorie":42.52411,"mOthersTime":0,"mRunTime":0,"mStartTime":31200000,"mTimeUnit":600000,"mWalkTime":600000,"runStep":0,"walkStep":1069},{"distance":810.47754,"mCalorie":42.52411,"mOthersTime":0,"mRunTime":0,"mStartTime":31800000,"mTimeUnit":600000,"mWalkTime":600000,"runStep":0,"walkStep":1065},{"distance":810.47754,"mCalorie":42.52411,"mOthersTime":0,"mRunTime":0,"mStartTime":32400000,"mTimeUnit":600000,"mWalkTime":600000,"runStep":0,"walkStep":1059},{"distance":810.47754,"mCalorie":42.52411,"mOthersTime":0,"mRunTime":0,"mStartTime":33000000,"mTimeUnit":600000,"mWalkTime":600000,"runStep":0,"walkStep":1046},{"distance":518.6301,"mCalorie":27.09956,"mOthersTime":0,"mRunTime":0,"mStartTime":33600000,"mTimeUnit":600000,"mWalkTime":385797,"runStep":0,"walkStep":654},{"distance":509.54004,"mCalorie":26.86,"mOthersTime":0,"mRunTime":0,"mStartTime":34200000,"mTimeUnit":600000,"mWalkTime":395381,"runStep":0,"walkStep":662},{"distance":81.08,"mCalorie":4.56,"mOthersTime":0,"mRunTime":0,"mStartTime":34800000,"mTimeUnit":600000,"mWalkTime":62031,"runStep":0,"walkStep":93},{"distance":151.38,"mCalorie":9.04,"mOthersTime":0,"mRunTime":9200,"mStartTime":35400000,"mTimeUnit":600000,"mWalkTime":78039,"runStep":23,"walkStep":117},{"distance":194.95999,"mCalorie":10.12,"mOthersTime":0,"mRunTime":6720,"mStartTime":36000000,"mTimeUnit":600000,"mWalkTime":135587,"runStep":18,"walkStep":211},{"distance":215.19,"mCalorie":11.379999,"mOthersTime":0,"mRunTime":0,"mStartTime":36600000,"mTimeUnit":600000,"mWalkTime":193430,"runStep":0,"walkStep":290},{"distance":32.760002,"mCalorie":1.71,"mOthersTime":0,"mRunTime":0,"mStartTime":37200000,"mTimeUnit":600000,"mWalkTime":30015,"runStep":0,"walkStep":45},{"distance":373.77,"mCalorie":21.25,"mOthersTime":0,"mRunTime":0,"mStartTime":37800000,"mTimeUnit":600000,"mWalkTime":346810,"runStep":0,"walkStep":520},{"distance":263.83,"mCalorie":16.429998,"mOthersTime":0,"mRunTime":21200,"mStartTime":38400000,"mTimeUnit":600000,"mWalkTime":102718,"runStep":53,"walkStep":154},{"distance":368.92,"mCalorie":23.11,"mOthersTime":0,"mRunTime":32400,"mStartTime":39000000,"mTimeUnit":600000,"mWalkTime":172086,"runStep":81,"walkStep":258},{"distance":31.52,"mCalorie":1.62,"mOthersTime":0,"mRunTime":0,"mStartTime":39600000,"mTimeUnit":600000,"mWalkTime":28681,"runStep":0,"walkStep":43},{"distance":119.41,"mCalorie":6.79,"mOthersTime":0,"mRunTime":5600,"mStartTime":40200000,"mTimeUnit":600000,"mWalkTime":64032,"runStep":14,"walkStep":96},{"distance":78.81999,"mCalorie":5.48,"mOthersTime":0,"mRunTime":800,"mStartTime":40800000,"mTimeUnit":600000,"mWalkTime":59363,"runStep":2,"walkStep":89},{"distance":321.63004,"mCalorie":15.109999,"mOthersTime":0,"mRunTime":7486,"mStartTime":48600000,"mTimeUnit":600000,"mWalkTime":209790,"runStep":20,"walkStep":334},{"distance":330.51,"mCalorie":18.83,"mOthersTime":0,"mRunTime":20800,"mStartTime":49200000,"mTimeUnit":600000,"mWalkTime":168084,"runStep":52,"walkStep":252},{"distance":240.71,"mCalorie":13.44,"mOthersTime":0,"mRunTime":9600,"mStartTime":49800000,"mTimeUnit":600000,"mWalkTime":137402,"runStep":24,"walkStep":206},{"distance":41.21,"mCalorie":3.01,"mOthersTime":0,"mRunTime":0,"mStartTime":50400000,"mTimeUnit":600000,"mWalkTime":43355,"runStep":0,"walkStep":65},{"distance":269.03998,"mCalorie":14.13,"mOthersTime":0,"mRunTime":6000,"mStartTime":51000000,"mTimeUnit":600000,"mWalkTime":178089,"runStep":15,"walkStep":267},{"distance":236.90001,"mCalorie":12.95,"mOthersTime":0,"mRunTime":6000,"mStartTime":51600000,"mTimeUnit":600000,"mWalkTime":152743,"runStep":15,"walkStep":229},{"distance":4.2,"mCalorie":0.22,"mOthersTime":0,"mRunTime":0,"mStartTime":52800000,"mTimeUnit":600000,"mWalkTime":4002,"runStep":0,"walkStep":6},{"distance":7.49,"mCalorie":0.37,"mOthersTime":0,"mRunTime":0,"mStartTime":54000000,"mTimeUnit":600000,"mWalkTime":6670,"runStep":0,"walkStep":10},{"distance":71.32,"mCalorie":3.77,"mOthersTime":0,"mRunTime":2800,"mStartTime":72600000,"mTimeUnit":600000,"mWalkTime":41354,"runStep":7,"walkStep":62},{"distance":15.03,"mCalorie":0.79,"mOthersTime":0,"mRunTime":0,"mStartTime":73200000,"mTimeUnit":600000,"mWalkTime":14007,"runStep":0,"walkStep":21},{"distance":24.529999,"mCalorie":1.37,"mOthersTime":0,"mRunTime":400,"mStartTime":73800000,"mTimeUnit":600000,"mWalkTime":14674,"runStep":1,"walkStep":22}],"version":1}